vat_moss/id.py
vat_moss/exchange_rates.py
vat_moss/billing_address.py
vat_moss/declared_residence.py
vat_moss/errors.py
vat_moss/rates.py
vat_moss/geoip2.py
vat_moss/__init__.py
vat_moss/phone_number.py
french_vat_moss-0.12.0.dist-info/WHEEL
french_vat_moss-0.12.0.dist-info/top_level.txt
french_vat_moss-0.12.0.dist-info/metadata.json
french_vat_moss-0.12.0.dist-info/METADATA
french_vat_moss-0.12.0.dist-info/RECORD
french_vat_moss-0.12.0.dist-info/DESCRIPTION.rst
