Metadata-Version: 2.0
Name: french-vat-moss
Version: 0.12.0
Summary: Tools for VAT MOSS and Norway VAT on digital services.
Home-page: https://github.com/laurentL/vat_moss-python
Author: Labatut Laurent
Author-email: laurent@labatut.net
License: MIT
Keywords: french vat
Platform: UNKNOWN
Classifier: Development Status :: 4 - Beta
Classifier: Intended Audience :: Developers
Classifier: License :: OSI Approved :: MIT License
Classifier: Programming Language :: Python :: 2.7
Classifier: Programming Language :: Python :: 3.3
Classifier: Programming Language :: Python :: 3.4
Requires-Dist: money
Requires-Dist: pythonsol
